rlberry_scool/__init__.py
rlberry_scool/_version.py
rlberry_scool/random_agent.py
rlberry_scool/agents/__init__.py
rlberry_scool/agents/dynprog/__init__.py
rlberry_scool/agents/dynprog/utils.py
rlberry_scool/agents/dynprog/value_iteration.py
rlberry_scool/agents/features/__init__.py
rlberry_scool/agents/features/feature_map.py
rlberry_scool/agents/linear/__init__.py
rlberry_scool/agents/linear/lsvi_ucb.py
rlberry_scool/agents/mbqvi/__init__.py
rlberry_scool/agents/mbqvi/mbqvi.py
rlberry_scool/agents/tabular_rl/__init__.py
rlberry_scool/agents/tabular_rl/qlearning.py
rlberry_scool/agents/tabular_rl/sarsa.py
rlberry_scool/agents/tests/__init__.py
rlberry_scool/agents/tests/test_dynprog.py
rlberry_scool/agents/tests/test_lsvi_ucb.py
rlberry_scool/agents/tests/test_mbqvi.py
rlberry_scool/agents/ucbvi/__init__.py
rlberry_scool/agents/ucbvi/exploration_tools_discrete_counter.py
rlberry_scool/agents/ucbvi/ucbvi.py
rlberry_scool/agents/ucbvi/utils.py
rlberry_scool/colab_utils/__init__.py
rlberry_scool/colab_utils/display_setup.py
rlberry_scool/envs/__init__.py
rlberry_scool/envs/finite/__init__.py
rlberry_scool/envs/finite/chain.py
rlberry_scool/envs/finite/discrete_mountain_car.py
rlberry_scool/envs/finite/gridworld.py
rlberry_scool/envs/finite/gridworld_utils.py
rlberry_scool/envs/tests/__init__.py
rlberry_scool/envs/tests/test_env_seeding.py
rlberry_scool/envs/tests/test_instantiation.py
rlberry_scool/envs/tests/test_rendering.py
rlberry_scool-0.7.3.dist-info/LICENSE
rlberry_scool-0.7.3.dist-info/METADATA
rlberry_scool-0.7.3.dist-info/WHEEL
rlberry_scool-0.7.3.dist-info/top_level.txt
rlberry_scool-0.7.3.dist-info/RECORD
